{"sdk_version":20,"bundle_id":"am.socialobjects.simpleapp.v1","start_timestamp":1506669796445.9299,"app_version_string":"4","device_uuid":"6B326BFF-EC4D-4439-8DBB-D0D9DC886A7E","simulator":false,"app_version":"14","is_our_crash_handler":1,"screen_height":736,"native_device_screen_width":1080,"native_device_screen_height":1920,"native_device_screen_scale":2.6086956521739131,"events":[{"id":879,"start_brightness_level":55,"device_orientation":5,"exit_screenshot_file_suffix":"1506669797469.45","exit_touch":{"id":0,"x":186,"timestamp":1506669797362.1699,"y":290,"screen_view_id":0,"target_frame":{"y":269,"w":125,"x":117,"h":72},"type":2,"phase":0,"target_class":"UIButton","tap_count":1,"target_name":"NEXT","hint":null,"dead_touch":false},"end_battery_level":7,"timestamp":1506669796547.4199,"screen_id":"dfa1766b25efb3cb84f890dd16aca2a552b11840","network_type":1,"type":1,"title":null,"end_brightness_level":55,"screen_orientation":0,"start_battery_level":7,"end_timestamp":1506669797469.45,"view_controller":"HMSomeController"},{"id":13235,"x":186,"timestamp":1506669797362.1699,"y":290,"screen_view_id":0,"type":2,"phase":0,"target_class":"UIButton","tap_count":1,"target_name":"NEXT","hint":null,"dead_touch":false},{"id":13236,"x":186,"timestamp":1506669797442.1899,"y":290,"screen_view_id":0,"type":2,"phase":3,"target_class":"UIButton","tap_count":1,"target_name":"NEXT","hint":null,"dead_touch":false},{"id":880,"start_brightness_level":55,"device_orientation":5,"exit_screenshot_file_suffix":"1506669805844.71","exit_touch":{"id":0,"x":358,"timestamp":1506669803960.7271,"y":507,"screen_view_id":880,"target_frame":{"y":0,"w":414,"x":0,"h":736},"type":2,"phase":0,"target_class":"UIView","tap_count":1,"target_name":"","hint":null,"dead_touch":true},"end_battery_level":8,"timestamp":1506669797607.9099,"screen_id":"31e2d9667575117c140d7815a40be2ddb7f79a74","network_type":1,"type":1,"title":null,"end_brightness_level":55,"screen_orientation":0,"start_battery_level":7,"end_timestamp":1506669805844.7102,"view_controller":"HMOtherController"},{"id":13237,"x":172,"timestamp":1506669798459.96,"y":207,"screen_view_id":0,"type":2,"phase":0,"target_class":"UISlider","tap_count":1,"target_name":"","hint":null,"dead_touch":false},{"id":13238,"x":181,"timestamp":1506669798475.3899,"y":204,"screen_view_id":0,"type":2,"phase":1,"target_class":"UISlider","tap_count":1,"target_name":"","hint":null,"dead_touch":false},{"id":13239,"x":194,"timestamp":1506669798492.3501,"y":198,"screen_view_id":0,"type":2,"phase":1,"target_class":"UISlider","tap_count":1,"target_name":"","hint":null,"dead_touch":false},{"id":13240,"x":210,"timestamp":1506669798508.8201,"y":194,"screen_view_id":0,"type":2,"phase":1,"target_class":"UISlider","tap_count":1,"target_name":"","hint":null,"dead_touch":false},{"id":13241,"x":249,"timestamp":1506669798552.3801,"y":186,"screen_view_id":0,"type":2,"phase":1,"target_class":"UISlider","tap_count":1,"target_name":"","hint":null,"dead_touch":false},{"id":13242,"x":267,"timestamp":1506669798558.7202,"y":181,"screen_view_id":0,"type":2,"phase":1,"target_class":"UISlider","tap_count":1,"target_name":"","hint":null,"dead_touch":false},{"id":13243,"x":269,"timestamp":1506669798575.3801,"y":179,"screen_view_id":0,"type":2,"phase":3,"target_class":"UISlider","tap_count":0,"target_name":"","hint":null,"dead_touch":false},{"id":13244,"x":138,"timestamp":1506669798776.71,"y":149,"screen_view_id":0,"type":2,"phase":0,"target_class":"UISlider","tap_count":1,"target_name":"","hint":null,"dead_touch":false},{"id":13245,"x":150,"timestamp":1506669798808.6299,"y":144,"screen_view_id":0,"type":2,"phase":1,"target_class":"UISlider","tap_count":1,"target_name":"","hint":null,"dead_touch":false},{"id":13246,"x":169,"timestamp":1506669798825.6299,"y":142,"screen_view_id":0,"type":2,"phase":1,"target_class":"UISlider","tap_count":1,"target_name":"","hint":null,"dead_touch":false},{"id":13247,"x":198,"timestamp":1506669798841.97,"y":138,"screen_view_id":0,"type":2,"phase":1,"target_class":"UISlider","tap_count":1,"target_name":"","hint":null,"dead_touch":false},{"id":13248,"x":233,"timestamp":1506669798858.9202,"y":134,"screen_view_id":0,"type":2,"phase":1,"target_class":"UISlider","tap_count":1,"target_name":"","hint":null,"dead_touch":false},{"id":13249,"x":259,"timestamp":1506669798876.02,"y":133,"screen_view_id":0,"type":2,"phase":1,"target_class":"UISlider","tap_count":1,"target_name":"","hint":null,"dead_touch":false},{"id":13250,"x":280,"timestamp":1506669798892.26,"y":131,"screen_view_id":0,"type":2,"phase":3,"target_class":"UISlider","tap_count":0,"target_name":"","hint":null,"dead_touch":false},{"id":13251,"x":178,"timestamp":1506669799193.4399,"y":275,"screen_view_id":0,"type":2,"phase":0,"target_class":"UISlider","tap_count":1,"target_name":"","hint":null,"dead_touch":false},{"id":13252,"x":168,"timestamp":1506669799225.8699,"y":273,"screen_view_id":0,"type":2,"phase":1,"target_class":"UISlider","tap_count":1,"target_name":"","hint":null,"dead_touch":false},{"id":13253,"x":156,"timestamp":1506669799242.51,"y":273,"screen_view_id":0,"type":2,"phase":1,"target_class":"UISlider","tap_count":1,"target_name":"","hint":null,"dead_touch":false},{"id":13254,"x":140,"timestamp":1506669799259.0498,"y":273,"screen_view_id":0,"type":2,"phase":1,"target_class":"UISlider","tap_count":1,"target_name":"","hint":null,"dead_touch":false},{"id":13255,"x":116,"timestamp":1506669799275.5798,"y":273,"screen_view_id":0,"type":2,"phase":1,"target_class":"UISlider","tap_count":1,"target_name":"","hint":null,"dead_touch":false},{"id":13256,"x":90,"timestamp":1506669799292.27,"y":273,"screen_view_id":0,"type":2,"phase":1,"target_class":"UISlider","tap_count":1,"target_name":"","hint":null,"dead_touch":false},{"id":13257,"x":68,"timestamp":1506669799308.76,"y":270,"screen_view_id":0,"type":2,"phase":1,"target_class":"UISlider","tap_count":1,"target_name":"","hint":null,"dead_touch":false},{"id":13258,"x":66,"timestamp":1506669799325.5701,"y":268,"screen_view_id":0,"type":2,"phase":3,"target_class":"UISlider","tap_count":0,"target_name":"","hint":null,"dead_touch":false},{"id":13259,"x":155,"timestamp":1506669799576.8999,"y":328,"screen_view_id":0,"type":2,"phase":0,"target_class":"UISlider","tap_count":1,"target_name":"","hint":null,"dead_touch":false},{"id":13260,"x":158,"timestamp":1506669799608.8901,"y":328,"screen_view_id":0,"type":2,"phase":1,"target_class":"UISlider","tap_count":1,"target_name":"","hint":null,"dead_touch":false},{"id":13261,"x":172,"timestamp":1506669799625.72,"y":326,"screen_view_id":0,"type":2,"phase":1,"target_class":"UISlider","tap_count":1,"target_name":"","hint":null,"dead_touch":false},{"id":13262,"x":197,"timestamp":1506669799642.4402,"y":320,"screen_view_id":0,"type":2,"phase":1,"target_class":"UISlider","tap_count":1,"target_name":"","hint":null,"dead_touch":false},{"id":13263,"x":223,"timestamp":1506669799659.04,"y":315,"screen_view_id":0,"type":2,"phase":1,"target_class":"UISlider","tap_count":1,"target_name":"","hint":null,"dead_touch":false},{"id":13264,"x":247,"timestamp":1506669799675.55,"y":310,"screen_view_id":0,"type":2,"phase":1,"target_class":"UISlider","tap_count":1,"target_name":"","hint":null,"dead_touch":false},{"id":13265,"x":269,"timestamp":1506669799692.3101,"y":305,"screen_view_id":0,"type":2,"phase":1,"target_class":"UISlider","tap_count":1,"target_name":"","hint":null,"dead_touch":false},{"id":13266,"x":271,"timestamp":1506669799708.8799,"y":303,"screen_view_id":0,"type":2,"phase":3,"target_class":"UISlider","tap_count":0,"target_name":"","hint":null,"dead_touch":false},{"id":13267,"x":192,"timestamp":1506669800293.51,"y":144,"screen_view_id":0,"type":2,"phase":0,"target_class":"UISlider","tap_count":1,"target_name":"","hint":null,"dead_touch":false},{"id":13268,"x":176,"timestamp":1506669800309.02,"y":144,"screen_view_id":0,"type":2,"phase":1,"target_class":"UISlider","tap_count":1,"target_name":"","hint":null,"dead_touch":false},{"id":13269,"x":155,"timestamp":1506669800325.79,"y":144,"screen_view_id":0,"type":2,"phase":1,"target_class":"UISlider","tap_count":1,"target_name":"","hint":null,"dead_touch":false},{"id":13270,"x":132,"timestamp":1506669800342.3801,"y":146,"screen_view_id":0,"type":2,"phase":1,"target_class":"UISlider","tap_count":1,"target_name":"","hint":null,"dead_touch":false},{"id":13271,"x":105,"timestamp":1506669800359.0801,"y":150,"screen_view_id":0,"type":2,"phase":1,"target_class":"UISlider","tap_count":1,"target_name":"","hint":null,"dead_touch":false},{"id":13272,"x":79,"timestamp":1506669800376.0901,"y":152,"screen_view_id":0,"type":2,"phase":1,"target_class":"UISlider","tap_count":1,"target_name":"","hint":null,"dead_touch":false},{"id":13273,"x":77,"timestamp":1506669800393.46,"y":154,"screen_view_id":0,"type":2,"phase":3,"target_class":"UISlider","tap_count":0,"target_name":"","hint":null,"dead_touch":false},{"id":13274,"x":218,"timestamp":1506669800712.3,"y":207,"screen_view_id":880,"type":2,"phase":0,"target_class":"UISlider","tap_count":1,"target_name":"","hint":null,"dead_touch":false},{"id":13275,"x":211,"timestamp":1506669800726.5798,"y":206,"screen_view_id":880,"type":2,"phase":1,"target_class":"UISlider","tap_count":1,"target_name":"","hint":null,"dead_touch":false},{"id":13276,"x":198,"timestamp":1506669800742.8701,"y":206,"screen_view_id":880,"type":2,"phase":1,"target_class":"UISlider","tap_count":1,"target_name":"","hint":null,"dead_touch":false},{"id":13277,"x":181,"timestamp":1506669800759.1299,"y":206,"screen_view_id":880,"type":2,"phase":1,"target_class":"UISlider","tap_count":1,"target_name":"","hint":null,"dead_touch":false},{"id":13278,"x":160,"timestamp":1506669800776.01,"y":206,"screen_view_id":880,"type":2,"phase":1,"target_class":"UISlider","tap_count":1,"target_name":"","hint":null,"dead_touch":false},{"id":13279,"x":137,"timestamp":1506669800792.6099,"y":206,"screen_view_id":880,"type":2,"phase":1,"target_class":"UISlider","tap_count":1,"target_name":"","hint":null,"dead_touch":false},{"id":13280,"x":114,"timestamp":1506669800809.51,"y":205,"screen_view_id":880,"type":2,"phase":1,"target_class":"UISlider","tap_count":1,"target_name":"","hint":null,"dead_touch":false},{"id":13281,"x":112,"timestamp":1506669800826.8599,"y":203,"screen_view_id":880,"type":2,"phase":3,"target_class":"UISlider","tap_count":0,"target_name":"","hint":null,"dead_touch":false},{"id":13282,"x":111,"timestamp":1506669801093.6201,"y":142,"screen_view_id":880,"type":2,"phase":0,"target_class":"UISlider","tap_count":1,"target_name":"","hint":null,"dead_touch":false},{"id":13283,"x":117,"timestamp":1506669801109.1799,"y":140,"screen_view_id":880,"type":2,"phase":1,"target_class":"UISlider","tap_count":1,"target_name":"","hint":null,"dead_touch":false},{"id":13284,"x":133,"timestamp":1506669801125.8198,"y":139,"screen_view_id":880,"type":2,"phase":1,"target_class":"UISlider","tap_count":1,"target_name":"","hint":null,"dead_touch":false},{"id":13285,"x":157,"timestamp":1506669801142.51,"y":138,"screen_view_id":880,"type":2,"phase":1,"target_class":"UISlider","tap_count":1,"target_name":"","hint":null,"dead_touch":false},{"id":13286,"x":196,"timestamp":1506669801159.46,"y":137,"screen_view_id":880,"type":2,"phase":1,"target_class":"UISlider","tap_count":1,"target_name":"","hint":null,"dead_touch":false},{"id":13287,"x":235,"timestamp":1506669801175.95,"y":137,"screen_view_id":880,"type":2,"phase":1,"target_class":"UISlider","tap_count":1,"target_name":"","hint":null,"dead_touch":false},{"id":13288,"x":271,"timestamp":1506669801192.46,"y":137,"screen_view_id":880,"type":2,"phase":1,"target_class":"UISlider","tap_count":1,"target_name":"","hint":null,"dead_touch":false},{"id":13289,"x":296,"timestamp":1506669801209.1201,"y":137,"screen_view_id":880,"type":2,"phase":1,"target_class":"UISlider","tap_count":1,"target_name":"","hint":null,"dead_touch":false},{"id":13290,"x":312,"timestamp":1506669801225.8899,"y":137,"screen_view_id":880,"type":2,"phase":1,"target_class":"UISlider","tap_count":1,"target_name":"","hint":null,"dead_touch":false},{"id":13291,"x":314,"timestamp":1506669801242.3999,"y":139,"screen_view_id":880,"type":2,"phase":3,"target_class":"UISlider","tap_count":0,"target_name":"","hint":null,"dead_touch":false},{"id":13292,"x":91,"timestamp":1506669801463.96,"y":207,"screen_view_id":880,"type":2,"phase":0,"target_class":"UISlider","tap_count":1,"target_name":"","hint":null,"dead_touch":false},{"id":13293,"x":115,"timestamp":1506669801475.71,"y":202,"screen_view_id":880,"type":2,"phase":1,"target_class":"UISlider","tap_count":1,"target_name":"","hint":null,"dead_touch":false},{"id":13294,"x":144,"timestamp":1506669801492.6702,"y":199,"screen_view_id":880,"type":2,"phase":1,"target_class":"UISlider","tap_count":1,"target_name":"","hint":null,"dead_touch":false},{"id":13295,"x":183,"timestamp":1506669801509.3201,"y":196,"screen_view_id":880,"type":2,"phase":1,"target_class":"UISlider","tap_count":1,"target_name":"","hint":null,"dead_touch":false},{"id":13296,"x":223,"timestamp":1506669801525.8901,"y":194,"screen_view_id":880,"type":2,"phase":1,"target_class":"UISlider","tap_count":1,"target_name":"","hint":null,"dead_touch":false},{"id":13297,"x":261,"timestamp":1506669801542.8501,"y":192,"screen_view_id":880,"type":2,"phase":1,"target_class":"UISlider","tap_count":1,"target_name":"","hint":null,"dead_touch":false},{"id":13298,"x":293,"timestamp":1506669801559.3901,"y":191,"screen_view_id":880,"type":2,"phase":1,"target_class":"UISlider","tap_count":1,"target_name":"","hint":null,"dead_touch":false},{"id":13299,"x":316,"timestamp":1506669801576.03,"y":190,"screen_view_id":880,"type":2,"phase":1,"target_class":"UISlider","tap_count":1,"target_name":"","hint":null,"dead_touch":false},{"id":13300,"x":318,"timestamp":1506669801592.78,"y":188,"screen_view_id":880,"type":2,"phase":3,"target_class":"UISlider","tap_count":0,"target_name":"","hint":null,"dead_touch":false},{"id":13301,"x":113,"timestamp":1506669801927.1299,"y":216,"screen_view_id":880,"type":2,"phase":0,"target_class":"UISlider","tap_count":1,"target_name":"","hint":null,"dead_touch":false},{"id":13302,"x":120,"timestamp":1506669801959.26,"y":213,"screen_view_id":880,"type":2,"phase":1,"target_class":"UISlider","tap_count":1,"target_name":"","hint":null,"dead_touch":false},{"id":13303,"x":136,"timestamp":1506669801976.01,"y":211,"screen_view_id":880,"type":2,"phase":1,"target_class":"UISlider","tap_count":1,"target_name":"","hint":null,"dead_touch":false},{"id":13304,"x":163,"timestamp":1506669801992.48,"y":208,"screen_view_id":880,"type":2,"phase":1,"target_class":"UISlider","tap_count":1,"target_name":"","hint":null,"dead_touch":false},{"id":13305,"x":197,"timestamp":1506669802009.3101,"y":205,"screen_view_id":880,"type":2,"phase":1,"target_class":"UISlider","tap_count":1,"target_name":"","hint":null,"dead_touch":false},{"id":13306,"x":224,"timestamp":1506669802025.8401,"y":204,"screen_view_id":880,"type":2,"phase":1,"target_class":"UISlider","tap_count":1,"target_name":"","hint":null,"dead_touch":false},{"id":13307,"x":251,"timestamp":1506669802042.71,"y":203,"screen_view_id":880,"type":2,"phase":1,"target_class":"UISlider","tap_count":1,"target_name":"","hint":null,"dead_touch":false},{"id":13308,"x":274,"timestamp":1506669802059.25,"y":203,"screen_view_id":880,"type":2,"phase":1,"target_class":"UISlider","tap_count":1,"target_name":"","hint":null,"dead_touch":false},{"id":13309,"x":289,"timestamp":1506669802075.8401,"y":202,"screen_view_id":880,"type":2,"phase":3,"target_class":"UISlider","tap_count":0,"target_name":"","hint":null,"dead_touch":false},{"id":13310,"x":113,"timestamp":1506669802377.2,"y":274,"screen_view_id":880,"type":2,"phase":0,"target_class":"UISlider","tap_count":1,"target_name":"","hint":null,"dead_touch":false},{"id":13311,"x":123,"timestamp":1506669802392.9199,"y":270,"screen_view_id":880,"type":2,"phase":1,"target_class":"UISlider","tap_count":1,"target_name":"","hint":null,"dead_touch":false},{"id":13312,"x":139,"timestamp":1506669802409.6101,"y":263,"screen_view_id":880,"type":2,"phase":1,"target_class":"UISlider","tap_count":1,"target_name":"","hint":null,"dead_touch":false},{"id":13313,"x":158,"timestamp":1506669802426.04,"y":259,"screen_view_id":880,"type":2,"phase":1,"target_class":"UISlider","tap_count":1,"target_name":"","hint":null,"dead_touch":false},{"id":13314,"x":179,"timestamp":1506669802442.8699,"y":257,"screen_view_id":880,"type":2,"phase":1,"target_class":"UISlider","tap_count":1,"target_name":"","hint":null,"dead_touch":false},{"id":13315,"x":197,"timestamp":1506669802459.47,"y":256,"screen_view_id":880,"type":2,"phase":1,"target_class":"UISlider","tap_count":1,"target_name":"","hint":null,"dead_touch":false},{"id":13316,"x":217,"timestamp":1506669802475.98,"y":256,"screen_view_id":880,"type":2,"phase":1,"target_class":"UISlider","tap_count":1,"target_name":"","hint":null,"dead_touch":false},{"id":13317,"x":235,"timestamp":1506669802492.5698,"y":256,"screen_view_id":880,"type":2,"phase":1,"target_class":"UISlider","tap_count":1,"target_name":"","hint":null,"dead_touch":false},{"id":13318,"x":247,"timestamp":1506669802509.3999,"y":254,"screen_view_id":880,"type":2,"phase":3,"target_class":"UISlider","tap_count":0,"target_name":"","hint":null,"dead_touch":false},{"id":13319,"x":194,"timestamp":1506669802695.52,"y":338,"screen_view_id":880,"type":2,"phase":0,"target_class":"UISlider","tap_count":1,"target_name":"","hint":null,"dead_touch":false},{"id":13320,"x":188,"timestamp":1506669802710.3,"y":337,"screen_view_id":880,"type":2,"phase":1,"target_class":"UISlider","tap_count":1,"target_name":"","hint":null,"dead_touch":false},{"id":13321,"x":176,"timestamp":1506669802726.9001,"y":337,"screen_view_id":880,"type":2,"phase":1,"target_class":"UISlider","tap_count":1,"target_name":"","hint":null,"dead_touch":false},{"id":13322,"x":158,"timestamp":1506669802743.8801,"y":337,"screen_view_id":880,"type":2,"phase":1,"target_class":"UISlider","tap_count":1,"target_name":"","hint":null,"dead_touch":false},{"id":13323,"x":132,"timestamp":1506669802760.4102,"y":337,"screen_view_id":880,"type":2,"phase":1,"target_class":"UISlider","tap_count":1,"target_name":"","hint":null,"dead_touch":false},{"id":13324,"x":103,"timestamp":1506669802776.5901,"y":337,"screen_view_id":880,"type":2,"phase":1,"target_class":"UISlider","tap_count":1,"target_name":"","hint":null,"dead_touch":false},{"id":13325,"x":73,"timestamp":1506669802793.48,"y":336,"screen_view_id":880,"type":2,"phase":1,"target_class":"UISlider","tap_count":1,"target_name":"","hint":null,"dead_touch":false},{"id":13326,"x":54,"timestamp":1506669802809.6199,"y":332,"screen_view_id":880,"type":2,"phase":1,"target_class":"UISlider","tap_count":1,"target_name":"","hint":null,"dead_touch":false},{"id":13327,"x":43,"timestamp":1506669802826.2898,"y":326,"screen_view_id":880,"type":2,"phase":1,"target_class":"UISlider","tap_count":1,"target_name":"","hint":null,"dead_touch":false},{"id":13328,"x":41,"timestamp":1506669802843.28,"y":324,"screen_view_id":880,"type":2,"phase":3,"target_class":"UISlider","tap_count":0,"target_name":"","hint":null,"dead_touch":false},{"id":13329,"x":228,"timestamp":1506669803027.8699,"y":268,"screen_view_id":880,"type":2,"phase":0,"target_class":"UIView","tap_count":1,"target_name":"","hint":null,"dead_touch":true},{"id":13330,"x":219,"timestamp":1506669803059.6599,"y":265,"screen_view_id":880,"type":2,"phase":1,"target_class":"UIView","tap_count":1,"target_name":"","hint":null,"dead_touch":true},{"id":13331,"x":209,"timestamp":1506669803076,"y":265,"screen_view_id":880,"type":2,"phase":1,"target_class":"UIView","tap_count":1,"target_name":"","hint":null,"dead_touch":true},{"id":13332,"x":197,"timestamp":1506669803092.71,"y":265,"screen_view_id":880,"type":2,"phase":1,"target_class":"UIView","tap_count":1,"target_name":"","hint":null,"dead_touch":true},{"id":13333,"x":181,"timestamp":1506669803109.3801,"y":265,"screen_view_id":880,"type":2,"phase":1,"target_class":"UIView","tap_count":1,"target_name":"","hint":null,"dead_touch":true},{"id":13334,"x":165,"timestamp":1506669803126.1001,"y":262,"screen_view_id":880,"type":2,"phase":1,"target_class":"UIView","tap_count":1,"target_name":"","hint":null,"dead_touch":true},{"id":13335,"x":163,"timestamp":1506669803142.9099,"y":260,"screen_view_id":880,"type":2,"phase":3,"target_class":"UIView","tap_count":0,"target_name":"","hint":null,"dead_touch":true},{"id":13336,"x":358,"timestamp":1506669803960.73,"y":507,"screen_view_id":880,"type":2,"phase":0,"target_class":"UIView","tap_count":1,"target_name":"","hint":null,"dead_touch":true},{"id":13337,"x":353,"timestamp":1506669803976.0398,"y":515,"screen_view_id":880,"type":2,"phase":1,"target_class":"UIView","tap_count":1,"target_name":"","hint":null,"dead_touch":true},{"id":13338,"x":348,"timestamp":1506669803992.7102,"y":526,"screen_view_id":880,"type":2,"phase":1,"target_class":"UIView","tap_count":1,"target_name":"","hint":null,"dead_touch":true},{"id":13339,"x":342,"timestamp":1506669804009.4099,"y":543,"screen_view_id":880,"type":2,"phase":1,"target_class":"UIView","tap_count":1,"target_name":"","hint":null,"dead_touch":true},{"id":13340,"x":334,"timestamp":1506669804026.21,"y":567,"screen_view_id":880,"type":2,"phase":1,"target_class":"UIView","tap_count":1,"target_name":"","hint":null,"dead_touch":true},{"id":13341,"x":329,"timestamp":1506669804042.8401,"y":591,"screen_view_id":880,"type":2,"phase":1,"target_class":"UIView","tap_count":1,"target_name":"","hint":null,"dead_touch":true},{"id":13342,"x":326,"timestamp":1506669804059.6599,"y":610,"screen_view_id":880,"type":2,"phase":1,"target_class":"UIView","tap_count":1,"target_name":"","hint":null,"dead_touch":true},{"id":13343,"x":324,"timestamp":1506669804076.1299,"y":622,"screen_view_id":880,"type":2,"phase":1,"target_class":"UIView","tap_count":1,"target_name":"","hint":null,"dead_touch":true},{"id":13344,"x":324,"timestamp":1506669804110.1001,"y":628,"screen_view_id":880,"type":2,"phase":3,"target_class":"UIView","tap_count":0,"target_name":"","hint":null,"dead_touch":true}],"locale":"en_SE","first_run":false,"app_id":"simpleapp-ashot-ios","signing_profile_type":1,"os":"ios","screen_width":414,"id":"1506669796445.93_6B326BFF-EC4D-4439-8DBB-D0D9DC886A7E","screen_scale":3,"has_video":false,"carrier":"283-05","tag":null,"end_timestamp":1506669805954.2798,"build_type":0,"jailbroken":false,"device_model":"iPhone7,1","os_version":"11.0","timezone_offset":14400}